MANIFEST.in
setup.cfg
setup.py
fonts/LICENSE.txt
fonts/README.txt
fonts/Roboto-Black.ttf
fonts/Roboto-Bold.ttf
fonts/Roboto-Light.ttf
fonts/Roboto-Medium.ttf
fonts/Roboto-Regular.ttf
fonts/Roboto-Thin.ttf
lcse_tools.egg-info/PKG-INFO
lcse_tools.egg-info/SOURCES.txt
lcse_tools.egg-info/dependency_links.txt
lcse_tools.egg-info/not-zip-safe
lcse_tools.egg-info/requires.txt
lcse_tools.egg-info/top_level.txt
lib/__init__.py
lib/image_util.py
lib/ppm_plots.py
src/check_missing.py
src/dpp_server.py
src/eval_pp.py
src/layer_images.py
src/plot_rprofiles.py
src/pngs2movies.py