Metadata-Version: 1.0
Name: lcse-tools
Version: 5.3
Summary: Misc tools
Home-page: UNKNOWN
Author: Stou Sandalski
Author-email: sandalski@astro.umn.edu
License: Apache 2.0
Keywords: utils
Platform: UNKNOWN
